budgea/__init__.py
budgea/api_client.py
budgea/configuration.py
budgea/exceptions.py
budgea/fields.py
budgea/rest.py
budgea/api/__init__.py
budgea/api/administration_api.py
budgea/api/authentication_api.py
budgea/api/banks_api.py
budgea/api/connections_api.py
budgea/api/default_api.py
budgea/api/documents_api.py
budgea/api/ocr_api.py
budgea/api/oidc_api.py
budgea/api/pfm_api.py
budgea/api/providers_api.py
budgea/api/recipients_api.py
budgea/api/terms_api.py
budgea/api/transfer_api.py
budgea/api/transfers_api.py
budgea/api/users_management_api.py
budgea/api/wealth_api.py
budgea/models/__init__.py
budgea/models/access.py
budgea/models/account.py
budgea/models/account_log.py
budgea/models/account_type.py
budgea/models/account_types.py
budgea/models/accounts_alert.py
budgea/models/alert.py
budgea/models/auth_confirm.py
budgea/models/auth_init.py
budgea/models/auth_jwt.py
budgea/models/auth_jwt_payload.py
budgea/models/auth_jwt_payload_payload.py
budgea/models/auth_provider.py
budgea/models/auth_register.py
budgea/models/auth_token.py
budgea/models/auth_token_access.py
budgea/models/auth_token_code.py
budgea/models/auth_token_renew.py
budgea/models/banks.py
budgea/models/categories.py
budgea/models/categorize_data.py
budgea/models/categorize_transaction.py
budgea/models/category.py
budgea/models/certificate.py
budgea/models/client.py
budgea/models/clients.py
budgea/models/config.py
budgea/models/config_log.py
budgea/models/config_logs.py
budgea/models/connection.py
budgea/models/connection_account.py
budgea/models/connection_account_loan.py
budgea/models/connection_bank.py
budgea/models/connection_informations.py
budgea/models/connection_log.py
budgea/models/connection_source.py
budgea/models/connection_sources.py
budgea/models/connection_subscription.py
budgea/models/connections.py
budgea/models/connector.py
budgea/models/connector_category.py
budgea/models/connector_logo.py
budgea/models/connector_source.py
budgea/models/connectors.py
budgea/models/currency.py
pybudgea-0.1.12.dist-info/METADATA
pybudgea-0.1.12.dist-info/WHEEL
pybudgea-0.1.12.dist-info/top_level.txt
pybudgea-0.1.12.dist-info/RECORD
