Metadata-Version: 2.1
Name: pybudgea
Version: 0.1.12
Summary: Budgea API Documentation
Home-page: 
Author: OpenAPI Generator community
Author-email: rienafairefr@gmail.com
Keywords: OpenAPI,OpenAPI-Generator,Budgea API Documentation
Requires-Dist: urllib3 (>=1.15)
Requires-Dist: six (>=1.10)
Requires-Dist: certifi
Requires-Dist: python-dateutil
Requires-Dist: marshmallow
